alphanum/__init__.py
alphanum/alphanum.py
alphanum-0.2.0.dist-info/LICENSE
alphanum-0.2.0.dist-info/WHEEL
alphanum-0.2.0.dist-info/METADATA
alphanum-0.2.0.dist-info/RECORD
