Metadata-Version: 2.1
Name: alphanum
Version: 0.2.0
Summary: Generates random alphanumeric strings.
Home-page: https://github.com/clpo13/alphanum
License: MIT
Keywords: string,random,pseudo-random,generator
Author: Cody Logan
Author-email: clpo13@gmail.com
Requires-Python: >=3.5,<4.0
Classifier: License :: OSI Approved :: MIT License
Classifier: Programming Language :: Python :: 3
Classifier: Programming Language :: Python :: 3.5
Classifier: Programming Language :: Python :: 3.6
Classifier: Programming Language :: Python :: 3.7
Classifier: Programming Language :: Python :: 3.8
Project-URL: Repository, https://github.com/clpo13/alphanum
